MultiScaleDeformableAttention.cp38-win_amd64.pyd
functions/__init__.py
functions/ms_deform_attn_func.py
modules/__init__.py
modules/ms_deform_attn.py
MultiScaleDeformableAttention_win-1.1.dist-info/METADATA
MultiScaleDeformableAttention_win-1.1.dist-info/WHEEL
MultiScaleDeformableAttention_win-1.1.dist-info/top_level.txt
MultiScaleDeformableAttention_win-1.1.dist-info/RECORD
