Metadata-Version: 2.1
Name: MultiScaleDeformableAttention-win
Version: 1.1
Summary: PyTorch Wrapper for CUDA Functions of Multi-Scale Deformable Attention
Home-page: https://github.com/fundamentalvision/Deformable-DETR
Author: Weijie Su
